{
    "all": {
        "include": {
            "all": [
                "zsh",
                "xrandr",
                "system76-scheduler",
                "python3-pip",
                "tldr"
            ]
        },
        "exclude": {
            "all": [
                "firefox",
                "firefox-langpacks",
                "gnome-classic-session",
                "gnome-tour",
                "yelp"
            ]
        }
    },
    "38": {
        "include": {
            "all": []
        },
        "exclude": {
            "all": []
        }
    },
    "39": {
        "include": {
            "all": []
        },
        "exclude": {
            "all": []
        }
    }
}
